chipmunks/__init__.py
chipmunks/agent.py
chipmunks/chips.py
chipmunks/cli.py
chipmunks/coder.py
chipmunks/config.py
chipmunks/domain.py
chipmunks/location.py
chipmunks/log.py
chipmunks/monitor.py
chipmunks/nginx.py
chipmunks/test/__init__.py
chipmunks/test/mock.py
chipmunks/test/nginx_mock.pid
chipmunks/test/test_agent.py
chipmunks/test/test_app.py
chipmunks/test/test_location.py
chipmunks/test/test_monitor.py
chipmunks/test/test_nginx.py
chipmunks/test/conf.d/ucenter.conf
chipmunks/test/mconf.d/.gitkeep
chipmunks-0.2.dist-info/METADATA
chipmunks-0.2.dist-info/WHEEL
chipmunks-0.2.dist-info/entry_points.txt
chipmunks-0.2.dist-info/top_level.txt
chipmunks-0.2.dist-info/RECORD
