Metadata-Version: 2.1
Name: chipmunks
Version: 0.2
Summary: Chipmunks is lightweight api gateway based on nginx.
Home-page: http://git.lingmao.tech/xiaoym/chipmunks
Author: Yuming.Xiao
Author-email: 514058722@qq.com
License: UNKNOWN
Platform: UNKNOWN
Requires-Python: >= 3.5
Requires-Dist: Jinja2 (>=2.11.2)
Requires-Dist: etcd3 (>=0.12.0)
Requires-Dist: docker (>=4.3.1)
